[
    {
        "name": "Among Us",
        "min_players": 7,
        "max_players": 15,
        "platforms": ["PC", "Mobile", "Switch"],
        "genre": "Social Deduction",
        "online": true
    },
    {
        "name": "Valorant",
        "min_players": 1,
        "max_players": 5,
        "platforms": ["PC"],
        "genre": "FPS",
        "online": true
    },
    {
        "name": "League of Legends",
        "min_players": 1,
        "max_players": 5,
        "platforms": ["PC"],
        "genre": "MOBA",
        "online": true
    },
    {
        "name": "Minecraft",
        "min_players": 1,
        "max_players": 100,
        "platforms": ["PC", "Console", "Mobile"],
        "genre": "Sandbox",
        "online": true
    },
    {
        "name": "Fall Guys",
        "min_players": 1,
        "max_players": 60,
        "platforms": ["PC", "Console"],
        "genre": "Party",
        "online": true
    },
    {
        "name": "Counter-Strike 2",
        "min_players": 1,
        "max_players": 5,
        "platforms": ["PC"],
        "genre": "FPS",
        "online": true
    },
    {
        "name": "Fortnite",
        "min_players": 1,
        "max_players": 100,
        "platforms": ["PC", "Console", "Mobile"],
        "genre": "Battle Royale",
        "online": true
    },
    {
        "name": "GTA Online",
        "min_players": 1,
        "max_players": 30,
        "platforms": ["PC", "Console"],
        "genre": "Open World",
        "online": true
    },
    {
        "name": "Apex Legends",
        "min_players": 1,
        "max_players": 3,
        "platforms": ["PC", "Console"],
        "genre": "Battle Royale",
        "online": true
    },
    {
        "name": "Destiny 2",
        "min_players": 1,
        "max_players": 6,
        "platforms": ["PC", "Console"],
        "genre": "MMO FPS",
        "online": true
    },
    {
        "name": "Lethal Company",
        "min_players": 1,
        "max_players": 4,
        "platforms": ["PC"],
        "genre": "Survival horror",
        "online": true
    },
    {
        "name": "FragPunk",
        "min_players": 1,
        "max_players": 5,
        "platforms": ["PC"],
        "genre": "FPS",
        "online": true
    },
    {
        "name": "100% Orange juice",
        "min_players": 2,
        "max_players": 4,
        "platforms": ["PC"],
        "genre": "relax",
        "online": true
    },
    {
        "name": "Ultimate Chicken Horse",
        "min_players": 2,
        "max_players": 4,
        "platforms": ["PC"],
        "genre": "Party",
        "online": true
    },
    {
        "name": "小動物餐吧",
        "min_players": 2,
        "max_players": 4,
        "platforms": ["PC"],
        "genre": "Party",
        "online": true
    },
    {
        "name": "Marvel Rivals",
        "min_players": 1,
        "max_players": 6,
        "platforms": ["PC"],
        "genre": "unknown",
        "online": true
    },
    {
        "name": "Fast Food Simulator: Prologue",
        "min_players": 1,
        "max_players": 5,
        "platforms": ["PC"],
        "genre": "Party",
        "online": true
    },
    {
        "name": "R.E.P.O",
        "min_players":2,
        "max_players":16,
        "platforms":["PC"],
        "genre": "Survival horror",
        "online":true
    },
    {
        "name":"PUBG",
        "min_players":1,
        "max_players":100,
        "platforms":["PC"],
        "genre":"Battle Royale",
        "online":true
    },
    {
        "name":"Monster Hunter Wilds",
        "min_players":1,
        "max_players":4,
        "platforms":["PC","Console"],
        "genre":"Hunting",
        "online":true
    },
    {
        "name":"Crab Game",
        "min_players":1,
        "max_players":4,
        "platforms":["PC"],
        "genre":"Battle Royale",
        "online":true
    },
    {
        "name":"Rust",
        "min_players":1,
        "max_players":100,
        "platforms":["PC"],
        "genre":"Open World",
        "online":true
    }
]
